easyweb/__init__.py
easyweb/__version__.py
easyweb/config.py
easyweb/plugin.py
easyweb-2024.12.10.dist-info/METADATA
easyweb-2024.12.10.dist-info/WHEEL
easyweb-2024.12.10.dist-info/entry_points.txt
easyweb-2024.12.10.dist-info/licenses/LICENSE
easyweb-2024.12.10.dist-info/RECORD
