Metadata-Version: 2.1
Name: easyweb
Version: 2024.12.10
Summary: UOS easyweb
Author-email: mikigo <huangmingqiang@uniontech.com>
License: GPL2.0
License-File: LICENSE
Requires-Python: >=3.7
Requires-Dist: playwright
Requires-Dist: pytest
